glowmarktha/__init__.py
glowmarktha/const.py
glowmarktha/house.py
glowmarktha-0.0.14.dist-info/LICENSE
glowmarktha-0.0.14.dist-info/METADATA
glowmarktha-0.0.14.dist-info/WHEEL
glowmarktha-0.0.14.dist-info/top_level.txt
glowmarktha-0.0.14.dist-info/RECORD
