Metadata-Version: 2.1
Name: glowmarktha
Version: 0.0.14
Summary: A package to gather smart meter data from Glowmarkt devices.
Home-page: https://github.com/tombrien/glowmarkt-ha
Author: Tom Brien
Author-email: tom@tombrien.io
Project-URL: Bug Tracker, https://github.com/tombrien/glowmarkt-ha/issues
Classifier: Programming Language :: Python :: 3
Classifier: License :: OSI Approved :: Apache Software License
Classifier: Operating System :: OS Independent
Requires-Python: >=3.10
License-File: LICENSE
Requires-Dist: httpx
